{
  "status": "release",
  "link": "https://www.amazon.co.jp/%E7%AB%9C%E3%81%AE%E5%AD%A6%E6%A0%A1%E3%81%AF%E5%B1%B1%E3%81%AE%E4%B8%8A-%E4%B9%9D%E4%BA%95%E8%AB%92%E5%AD%90-ebook/dp/B00DLT047Q/ref=sr_1_1?__mk_ja_JP=%E3%82%AB%E3%82%BF%E3%82%AB%E3%83%8A&crid=HJ20B09KBC55&keywords=%E4%B9%9D%E4%BA%95+%E8%AB%92%E5%AD%90&qid=1646816873&sprefix=%E4%B9%9D%E4%BA%95+%E8%AB%92%E5%AD%90%2Caps%2C163&sr=8-1",
  "title_ko": "용의 학교는 산 위에",
  "title_ja": "竜の学校は山の上",
  "author": [
    "146"
  ],
  "author_ko": [
    "쿠이 료코"
  ],
  "author_ja": [
    "九井諒子"
  ],
  "cover": "./assets/160.jpeg"
}